utz/__init__.py
utz/argparse.py
utz/backoff.py
utz/bases.py
utz/case.py
utz/cd.py
utz/cli.py
utz/collections.py
utz/colors.py
utz/context.py
utz/dataclasses.py
utz/defaultdict.py
utz/df_counts.py
utz/diff_dfs.py
utz/environ.py
utz/escape.py
utz/fn.py
utz/gzip.py
utz/hash.py
utz/imports.py
utz/jsn.py
utz/mem.py
utz/methods.py
utz/o.py
utz/parallel.py
utz/path.py
utz/pdf.py
utz/plots.py
utz/pnds.py
utz/rgx.py
utz/s3.py
utz/setup.py
utz/size.py
utz/sql.py
utz/ssh.py
utz/test.py
utz/time.py
utz/tmpdir.py
utz/use.py
utz/version.py
utz/ym.py
utz/ymd.py
utz/zip.py
utz/aio/__init__.py
utz/aio/proc.py
utz/docker/__init__.py
utz/docker/dsl.py
utz/docker/file.py
utz/docker/image.py
utz/docker/util.py
utz/git/__init__.py
utz/git/_checkout.py
utz/git/branch.py
utz/git/clone.py
utz/git/ctx.py
utz/git/diff.py
utz/git/gist.py
utz/git/github.py
utz/git/head.py
utz/git/log.py
utz/git/remote.py
utz/git/repo.py
utz/git/status.py
utz/git/submodule.py
utz/git/tag.py
utz/proc/__init__.py
utz/proc/aio.py
utz/process/__init__.py
utz/process/aio.py
utz/process/cmd.py
utz/process/log.py
utz/process/named_pipes.py
utz/process/pipeline.py
utz/process/util.py
utz-0.21.5.dist-info/licenses/LICENSE
utz-0.21.5.dist-info/METADATA
utz-0.21.5.dist-info/WHEEL
utz-0.21.5.dist-info/top_level.txt
utz-0.21.5.dist-info/RECORD
