Metadata-Version: 2.4
Name: utz
Version: 0.21.5
Summary: *("yoots")*: utilities augmenting the Python standard library; processes, Pytest, Pandas, Plotly, …
Home-page: https://github.com/runsascoded/utz
Author: Ryan Williams
Author-email: ryan@runsascoded.com
License: MIT
Classifier: Programming Language :: Python :: 3
Classifier: Operating System :: OS Independent
Classifier: License :: OSI Approved :: MIT License
Requires-Python: >=3.10
License-File: LICENSE
Requires-Dist: stdlb>=0.1.1
Provides-Extra: cli
Requires-Dist: click; extra == "cli"
Provides-Extra: dt
Requires-Dist: click; extra == "dt"
Requires-Dist: python-dateutil; extra == "dt"
Requires-Dist: pytz; extra == "dt"
Provides-Extra: git
Requires-Dist: click; extra == "git"
Requires-Dist: GitPython; extra == "git"
Requires-Dist: PyGithub; extra == "git"
Provides-Extra: mem
Requires-Dist: memray; extra == "mem"
Provides-Extra: pd
Requires-Dist: numpy; extra == "pd"
Requires-Dist: pandas; extra == "pd"
Provides-Extra: pdf
Requires-Dist: reportlab; extra == "pdf"
Requires-Dist: pyPDF2; extra == "pdf"
Provides-Extra: plot
Requires-Dist: jupyter; extra == "plot"
Requires-Dist: kaleido; extra == "plot"
Requires-Dist: plotly; extra == "plot"
Provides-Extra: s3
Requires-Dist: boto3; extra == "s3"
Requires-Dist: botocore; extra == "s3"
Provides-Extra: setup
Requires-Dist: setuptools; extra == "setup"
Provides-Extra: size
Requires-Dist: humanize; extra == "size"
Provides-Extra: test
Requires-Dist: pytest; extra == "test"
Requires-Dist: pytest-mock; extra == "test"
Requires-Dist: python-dateutil==2.9.0; extra == "test"
Provides-Extra: all
Requires-Dist: pyyaml; extra == "all"
Requires-Dist: click; extra == "all"
Requires-Dist: click; extra == "all"
Requires-Dist: python-dateutil; extra == "all"
Requires-Dist: pytz; extra == "all"
Requires-Dist: click; extra == "all"
Requires-Dist: GitPython; extra == "all"
Requires-Dist: PyGithub; extra == "all"
Requires-Dist: memray; extra == "all"
Requires-Dist: numpy; extra == "all"
Requires-Dist: pandas; extra == "all"
Requires-Dist: reportlab; extra == "all"
Requires-Dist: pyPDF2; extra == "all"
Requires-Dist: jupyter; extra == "all"
Requires-Dist: kaleido; extra == "all"
Requires-Dist: plotly; extra == "all"
Requires-Dist: boto3; extra == "all"
Requires-Dist: botocore; extra == "all"
Requires-Dist: setuptools; extra == "all"
Requires-Dist: humanize; extra == "all"
Requires-Dist: pytest; extra == "all"
Requires-Dist: pytest-mock; extra == "all"
Requires-Dist: python-dateutil==2.9.0; extra == "all"
Dynamic: author
Dynamic: author-email
Dynamic: classifier
Dynamic: description
Dynamic: description-content-type
Dynamic: home-page
Dynamic: license
Dynamic: license-file
Dynamic: provides-extra
Dynamic: requires-dist
Dynamic: requires-python
Dynamic: summary
